{
  "dir": "apps/web/.next",
  "scannedFiles": 259,
  "rawMatches": 731,
  "matches": [
    {
      "generatedFile": "apps/web/.next/server/chunks/5002.js",
      "generatedIndex": 2609,
      "generatedMatch": "Yjs",
      "generatedLine": 1,
      "generatedColumn": 2609,
      "source": "webpack:///pages/offline-demo.client.tsx",
      "sourceLine": 51,
      "sourceColumn": 18,
      "sourceName": null,
      "snippet": ")(\"ul\",{children:[i.jsx(\"li\",{children:\"WebSocket-based live collaboration with Yjs\"}),i.jsx(\"li\",{children:\"User awareness and presence indicators\"}),i.jsx(\"li\",{children:\"Conflict-free document merg",
      "strong": false
    },
    {
      "generatedFile": "apps/web/.next/server/chunks/5002.js",
      "generatedIndex": 4747,
      "generatedMatch": "Yjs",
      "generatedLine": 1,
      "generatedColumn": 4747,
      "source": "webpack:///pages/offline-demo.client.tsx",
      "sourceLine": 124,
      "sourceColumn": 14,
      "sourceName": null,
      "snippet": " Context-Aware AI Assistant\"}),i.jsx(\"li\",{children:\"✅ Real-time Collaboration (Yjs + WebSocket)\"}),i.jsx(\"li\",{children:\"✅ Offline Persistence (IndexedDB)\"}),i.jsx(\"li\",{children:\"✅ Cross-Platform Su",
      "strong": false
    },
    {
      "generatedFile": "apps/web/.next/server/chunks/6033.js",
      "generatedIndex": 29798,
      "generatedMatch": "Y",
      "generatedLine": 1,
      "generatedColumn": 29798,
      "source": "webpack:///src/shared/lib/router/router.ts",
      "sourceLine": 1263,
      "sourceColumn": 29,
      "sourceName": "scroll",
      "snippet": "!1;let K=X.locale;d.ST&&performance.mark(\"routeChange\");let{shallow:$=!1,scroll:Y=!0}=n,Q={shallow:$};this._inFlightRoute&&this.clc&&(V||G.events.emit(\"routeChangeError\",M(),this._inFlightRoute,Q),thi",
      "strong": false
    },
    {
      "generatedFile": "apps/web/.next/server/chunks/6033.js",
      "generatedIndex": 30302,
      "generatedMatch": "Y",
      "generatedLine": 1,
      "generatedColumn": 30302,
      "source": "webpack:///src/shared/lib/router/router.ts",
      "sourceLine": 1305,
      "sourceColumn": 10,
      "sourceName": "scroll",
      "snippet": "J,G.events.emit(\"hashChangeStart\",r,Q),this.changeState(e,t,r,{...n,scroll:!1}),Y&&this.scrollToHash(J);try{await this.set(X,this.components[X.route],null)}catch(e){throw(0,l.default)(e)&&e.cancelled&",
      "strong": false
    },
    {
      "generatedFile": "apps/web/.next/server/chunks/8839.js",
      "generatedIndex": 8399,
      "generatedMatch": "Yjs",
      "generatedLine": 1,
      "generatedColumn": 8399,
      "source": "webpack:///pages/index.client.tsx",
      "sourceLine": 563,
      "sourceColumn": 10,
      "sourceName": null,
      "snippet": "{children:c})]})]}),(0,r.jsxs)(\"h2\",{children:[\"Collaborative editor powered by Yjs. Room: \",l,\", Document: \",c]}),o&&(0,r.jsxs)(x.Kq,{gap:\"small\",children:[(0,r.jsxs)(\"div\",{style:{border:\"1px solid ",
      "strong": false
    },
    {
      "generatedFile": "apps/web/.next/server/chunks/9185.js",
      "generatedIndex": 17392,
      "generatedMatch": "Y",
      "generatedLine": 6,
      "generatedColumn": 4305,
      "source": "webpack:///src/shared/lib/constants.ts",
      "sourceLine": 70,
      "sourceColumn": 13,
      "sourceName": "INTERCEPTION_ROUTE_REWRITE_MANIFEST",
      "snippet": "FEST:function(){return b},INTERCEPTION_ROUTE_REWRITE_MANIFEST:function(){return Y},MIDDLEWARE_BUILD_MANIFEST:function(){return G},MIDDLEWARE_MANIFEST:function(){return v},MIDDLEWARE_REACT_LOADABLE_MAN",
      "strong": false
    },
    {
      "generatedFile": "apps/web/.next/server/chunks/9185.js",
      "generatedIndex": 19904,
      "generatedMatch": "Y",
      "generatedLine": 6,
      "generatedColumn": 6817,
      "source": "webpack:///src/shared/lib/constants.ts",
      "sourceLine": 70,
      "sourceColumn": 13,
      "sourceName": "INTERCEPTION_ROUTE_REWRITE_MANIFEST",
      "snippet": "-manifest\",G=\"middleware-build-manifest\",z=\"middleware-react-loadable-manifest\",Y=\"interception-route-rewrite-manifest\",V=\"main\",X=\"\"+V+\"-app\",K=\"app-pages-internals\",Z=\"react-refresh\",q=\"amp\",J=\"webp",
      "strong": false
    },
    {
      "generatedFile": "apps/web/.next/static/chunks/1549.20a187cf366c5a52.js",
      "generatedIndex": 6325,
      "generatedMatch": "Yjs",
      "generatedLine": 1,
      "generatedColumn": 6325,
      "source": "webpack:///pages/index.client.tsx",
      "sourceLine": 227,
      "sourceColumn": 20,
      "sourceName": null,
      "snippet": "f(\"change\",a),o.destroy(),t.destroy()}}catch(e){console.error(\"Error setting up Yjs:\",e)}},[c,b,n,Y]);let X=e=>{if(B.current)try{let n=e.map(e=>({range:{startLineNumber:e.cursor.line,startColumn:e.cur",
      "strong": false
    },
    {
      "generatedFile": "apps/web/.next/static/chunks/1549.20a187cf366c5a52.js",
      "generatedIndex": 10940,
      "generatedMatch": "Yjs",
      "generatedLine": 1,
      "generatedColumn": 10940,
      "source": "webpack:///pages/index.client.tsx",
      "sourceLine": 563,
      "sourceColumn": 10,
      "sourceName": null,
      "snippet": "{children:b})]})]}),(0,o.jsxs)(\"h2\",{children:[\"Collaborative editor powered by Yjs. Room: \",c,\", Document: \",b]}),a&&(0,o.jsxs)(h.Kq,{gap:\"small\",children:[(0,o.jsxs)(\"div\",{style:{border:\"1px solid ",
      "strong": false
    },
    {
      "generatedFile": "apps/web/.next/static/chunks/1549.20a187cf366c5a52.js",
      "generatedIndex": 5053,
      "generatedMatch": "Y",
      "generatedLine": 1,
      "generatedColumn": 5053,
      "source": "webpack:///pages/index.client.tsx",
      "sourceLine": 114,
      "sourceColumn": 9,
      "sourceName": "userId",
      "snippet": "useRef)(null),B=(0,d.useRef)(null),Z=(0,d.useRef)(!1),[J,Q]=(0,d.useState)([]),[Y]=(0,d.useState)(()=>(0,m.Z)().substring(0,5));(0,d.useEffect)(()=>{l(!0);let n=localStorage.getItem(\"userName\");n?r(n)",
      "strong": false
    },
    {
      "generatedFile": "apps/web/.next/static/chunks/1549.20a187cf366c5a52.js",
      "generatedIndex": 6045,
      "generatedMatch": "Y",
      "generatedLine": 1,
      "generatedColumn": 6045,
      "source": "webpack:///pages/index.client.tsx",
      "sourceLine": 208,
      "sourceColumn": 12,
      "sourceName": "userId",
      "snippet": "r(\"Error updating user list:\",e),Q([])}};return i.setLocalStateField(\"user\",{id:Y,name:n,color:function(){let e=\"#\";for(let n=0;n<6;n++)e+=\"0123456789ABCDEF\"[Math.floor(16*Math.random())];return e}()}",
      "strong": false
    },
    {
      "generatedFile": "apps/web/.next/static/chunks/1549.20a187cf366c5a52.js",
      "generatedIndex": 6343,
      "generatedMatch": "Y",
      "generatedLine": 1,
      "generatedColumn": 6343,
      "source": "webpack:///pages/index.client.tsx",
      "sourceLine": 229,
      "sourceColumn": 31,
      "sourceName": "userId",
      "snippet": "stroy(),t.destroy()}}catch(e){console.error(\"Error setting up Yjs:\",e)}},[c,b,n,Y]);let X=e=>{if(B.current)try{let n=e.map(e=>({range:{startLineNumber:e.cursor.line,startColumn:e.cursor.column,endLine",
      "strong": false
    },
    {
      "generatedFile": "apps/web/.next/static/chunks/1549.20a187cf366c5a52.js",
      "generatedIndex": 16331,
      "generatedMatch": "Y",
      "generatedLine": 1,
      "generatedColumn": 16331,
      "source": "webpack:///pages/index.client.tsx",
      "sourceLine": 816,
      "sourceColumn": 57,
      "sourceName": "userId",
      "snippet": "px\",zIndex:1e3,maxWidth:\"300px\"},children:(0,o.jsx)(h.JG,{users:J,currentUserId:Y})})]}):(0,o.jsx)(\"div\",{children:\"Loading...\"})}}}]);\n//# sourceMappingURL=1549.20a187cf366c5a52.js.map",
      "strong": false
    },
    {
      "generatedFile": "apps/web/.next/static/chunks/3813.c051cb750efc3ede.js",
      "generatedIndex": 1762,
      "generatedMatch": "Yjs",
      "generatedLine": 1,
      "generatedColumn": 1762,
      "source": "webpack:///pages/offline-demo.client.tsx",
      "sourceLine": 51,
      "sourceColumn": 18,
      "sourceName": null,
      "snippet": "l\",{children:[(0,a.jsx)(\"li\",{children:\"WebSocket-based live collaboration with Yjs\"}),(0,a.jsx)(\"li\",{children:\"User awareness and presence indicators\"}),(0,a.jsx)(\"li\",{children:\"Conflict-free docum",
      "strong": false
    },
    {
      "generatedFile": "apps/web/.next/static/chunks/3813.c051cb750efc3ede.js",
      "generatedIndex": 3962,
      "generatedMatch": "Yjs",
      "generatedLine": 1,
      "generatedColumn": 3962,
      "source": "webpack:///pages/offline-demo.client.tsx",
      "sourceLine": 124,
      "sourceColumn": 14,
      "sourceName": null,
      "snippet": "text-Aware AI Assistant\"}),(0,a.jsx)(\"li\",{children:\"✅ Real-time Collaboration (Yjs + WebSocket)\"}),(0,a.jsx)(\"li\",{children:\"✅ Offline Persistence (IndexedDB)\"}),(0,a.jsx)(\"li\",{children:\"✅ Cross-Pla",
      "strong": false
    },
    {
      "generatedFile": "apps/web/.next/static/chunks/687.50975500d91e0ee5.js",
      "generatedIndex": 1486,
      "generatedMatch": "Yjs",
      "generatedLine": 1,
      "generatedColumn": 1486,
      "source": "webpack:///pages/minimal.client.tsx",
      "sourceLine": 117,
      "sourceColumn": 20,
      "sourceName": null,
      "snippet": "f(\"change\",l),n.destroy(),e.destroy()}}catch(e){console.error(\"Error setting up Yjs:\",e)}},[f,r,o]),r&&o)?(0,t.jsxs)(\"div\",{style:{padding:\"20px\"},children:[(0,t.jsx)(i(),{children:(0,t.jsx)(\"title\",{",
      "strong": false
    },
    {
      "generatedFile": "apps/web/.next/static/chunks/main-6488d641196effad.js",
      "generatedIndex": 8535,
      "generatedMatch": "Y",
      "generatedLine": 1,
      "generatedColumn": 8535,
      "source": "webpack:///src/client/index.tsx",
      "sourceLine": 99,
      "sourceColumn": 6,
      "sourceName": "Container",
      "snippet": ",G=_._(r(85009)),q=\"14.2.32\",X=(0,v.default)(),V=e=>[].slice.call(e),z=!1;class Y extends y.default.Component{componentDidCatch(e,t){this.props.fn(e,t)}componentDidMount(){this.scrollToHash(),n.isSsr&",
      "strong": false
    },
    {
      "generatedFile": "apps/web/.next/static/chunks/main-6488d641196effad.js",
      "generatedIndex": 10126,
      "generatedMatch": "Y",
      "generatedLine": 1,
      "generatedColumn": 10126,
      "source": "webpack:///src/client/index.tsx",
      "sourceLine": 305,
      "sourceColumn": 5,
      "sourceName": "Container",
      "snippet": ",o=y.default.useMemo(()=>(0,k.adaptForAppRouterInstance)(n),[]);return(0,g.jsx)(Y,{fn:e=>Z({App:f,err:e}).catch(e=>console.error(\"Error rendering page: \",e)),children:(0,g.jsx)(U.AppRouterContext.Prov",
      "strong": false
    },
    {
      "generatedFile": "apps/web/.next/static/chunks/main-6488d641196effad.js",
      "generatedIndex": 45644,
      "generatedMatch": "Y",
      "generatedLine": 1,
      "generatedColumn": 45644,
      "source": "webpack:///src/shared/lib/constants.ts",
      "sourceLine": 75,
      "sourceColumn": 13,
      "sourceName": "CLIENT_STATIC_FILES_RUNTIME_MAIN_APP",
      "snippet": "AIN:function(){return z},CLIENT_STATIC_FILES_RUNTIME_MAIN_APP:function(){return Y},CLIENT_STATIC_FILES_RUNTIME_POLYFILLS:function(){return Z},CLIENT_STATIC_FILES_RUNTIME_POLYFILLS_SYMBOL:function(){re",
      "strong": false
    },
    {
      "generatedFile": "apps/web/.next/static/chunks/main-6488d641196effad.js",
      "generatedIndex": 49130,
      "generatedMatch": "Y",
      "generatedLine": 1,
      "generatedColumn": 49130,
      "source": "webpack:///src/shared/lib/constants.ts",
      "sourceLine": 75,
      "sourceColumn": 13,
      "sourceName": "CLIENT_STATIC_FILES_RUNTIME_MAIN_APP",
      "snippet": "eware-react-loadable-manifest\",V=\"interception-route-rewrite-manifest\",z=\"main\",Y=\"\"+z+\"-app\",K=\"app-pages-internals\",$=\"react-refresh\",Q=\"amp\",J=\"webpack\",Z=\"polyfills\",ee=Symbol(Z),et=\"webpack-runti",
      "strong": false
    },
    {
      "generatedFile": "apps/web/.next/static/chunks/main-6488d641196effad.js",
      "generatedIndex": 50086,
      "generatedMatch": "Y",
      "generatedLine": 1,
      "generatedColumn": 50086,
      "source": "webpack:///src/shared/lib/constants.ts",
      "sourceLine": 147,
      "sourceColumn": 2,
      "sourceName": "CLIENT_STATIC_FILES_RUNTIME_MAIN_APP",
      "snippet": "rmStreamDefaultController\",\"WritableStreamDefaultController\"],eh=new Set([z,$,Q,Y]);(\"function\"==typeof t.default||\"object\"==typeof t.default&&null!==t.default)&&void 0===t.default.__esModule&&(Object",
      "strong": false
    },
    {
      "generatedFile": "apps/web/.next/static/chunks/main-6488d641196effad.js",
      "generatedIndex": 65983,
      "generatedMatch": "Y",
      "generatedLine": 1,
      "generatedColumn": 65983,
      "source": "webpack:///src/shared/lib/router/router.ts",
      "sourceLine": 1168,
      "sourceColumn": 10,
      "sourceName": "prevLocale",
      "snippet": "this.isReady=!0;let z=this.isSsr;if(H||(this.isSsr=!1),H&&this.clc)return!1;let Y=G.locale;d.ST&&performance.mark(\"routeChange\");let{shallow:K=!1,scroll:$=!0}=n,Q={shallow:K};this._inFlightRoute&&this",
      "strong": false
    },
    {
      "generatedFile": "apps/web/.next/static/chunks/main-6488d641196effad.js",
      "generatedIndex": 66422,
      "generatedMatch": "Y",
      "generatedLine": 1,
      "generatedColumn": 66422,
      "source": "webpack:///src/shared/lib/router/router.ts",
      "sourceLine": 1292,
      "sourceColumn": 25,
      "sourceName": "prevLocale",
      "snippet": "hasBasePath)(r)?(0,v.removeBasePath)(r):r,G.locale);this._inFlightRoute=r;let Z=Y!==G.locale;if(!H&&this.onlyAHashChange(J)&&!Z){G.asPath=J,V.events.emit(\"hashChangeStart\",r,Q),this.changeState(e,t,r,",
      "strong": false
    },
    {
      "generatedFile": "apps/web/.next/static/chunks/pages/index.client-3f92225fd0aca797.js",
      "generatedIndex": 6443,
      "generatedMatch": "Yjs",
      "generatedLine": 1,
      "generatedColumn": 6443,
      "source": "webpack:///pages/index.client.tsx",
      "sourceLine": 227,
      "sourceColumn": 20,
      "sourceName": null,
      "snippet": "f(\"change\",l),o.destroy(),n.destroy()}}catch(e){console.error(\"Error setting up Yjs:\",e)}},[c,x,t,Q]);let Y=e=>{if(B.current)try{let t=e.map(e=>({range:{startLineNumber:e.cursor.line,startColumn:e.cur",
      "strong": false
    },
    {
      "generatedFile": "apps/web/.next/static/chunks/pages/index.client-3f92225fd0aca797.js",
      "generatedIndex": 11058,
      "generatedMatch": "Yjs",
      "generatedLine": 1,
      "generatedColumn": 11058,
      "source": "webpack:///pages/index.client.tsx",
      "sourceLine": 563,
      "sourceColumn": 10,
      "sourceName": null,
      "snippet": "{children:x})]})]}),(0,o.jsxs)(\"h2\",{children:[\"Collaborative editor powered by Yjs. Room: \",c,\", Document: \",x]}),l&&(0,o.jsxs)(h.Kq,{gap:\"small\",children:[(0,o.jsxs)(\"div\",{style:{border:\"1px solid ",
      "strong": false
    },
    {
      "generatedFile": "apps/web/.next/static/chunks/pages/index.client-3f92225fd0aca797.js",
      "generatedIndex": 6037,
      "generatedMatch": "Y",
      "generatedLine": 1,
      "generatedColumn": 6037,
      "source": "webpack:///pages/index.client.tsx",
      "sourceLine": 199,
      "sourceColumn": 12,
      "sourceName": "updateCursorDecorations",
      "snippet": "d),name:String(e.name),color:String(e.color),cursor:e.cursor}));J(t),B.current&&Y(t.filter(e=>e.cursor))}catch(e){console.error(\"Error updating user list:\",e),J([])}};return i.setLocalStateField(\"user",
      "strong": false
    },
    {
      "generatedFile": "apps/web/.next/static/chunks/pages/index.client-3f92225fd0aca797.js",
      "generatedIndex": 6469,
      "generatedMatch": "Y",
      "generatedLine": 1,
      "generatedColumn": 6469,
      "source": "webpack:///pages/index.client.tsx",
      "sourceLine": 231,
      "sourceColumn": 8,
      "sourceName": "updateCursorDecorations",
      "snippet": "n.destroy()}}catch(e){console.error(\"Error setting up Yjs:\",e)}},[c,x,t,Q]);let Y=e=>{if(B.current)try{let t=e.map(e=>({range:{startLineNumber:e.cursor.line,startColumn:e.cursor.column,endLineNumber:e",
      "strong": false
    },
    {
      "generatedFile": "apps/web/.next/static/chunks/pages/minimal.client-dc16bd5faf0f35b4.js",
      "generatedIndex": 1604,
      "generatedMatch": "Yjs",
      "generatedLine": 1,
      "generatedColumn": 1604,
      "source": "webpack:///pages/minimal.client.tsx",
      "sourceLine": 117,
      "sourceColumn": 20,
      "sourceName": null,
      "snippet": "f(\"change\",l),n.destroy(),e.destroy()}}catch(e){console.error(\"Error setting up Yjs:\",e)}},[h,r,o]),r&&o)?(0,t.jsxs)(\"div\",{style:{padding:\"20px\"},children:[(0,t.jsx)(i(),{children:(0,t.jsx)(\"title\",{",
      "strong": false
    },
    {
      "generatedFile": "apps/web/.next/static/chunks/pages/offline-demo.client-b0af77c9a59f71e5.js",
      "generatedIndex": 1892,
      "generatedMatch": "Yjs",
      "generatedLine": 1,
      "generatedColumn": 1892,
      "source": "webpack:///pages/offline-demo.client.tsx",
      "sourceLine": 51,
      "sourceColumn": 18,
      "sourceName": null,
      "snippet": "l\",{children:[(0,l.jsx)(\"li\",{children:\"WebSocket-based live collaboration with Yjs\"}),(0,l.jsx)(\"li\",{children:\"User awareness and presence indicators\"}),(0,l.jsx)(\"li\",{children:\"Conflict-free docum",
      "strong": false
    },
    {
      "generatedFile": "apps/web/.next/static/chunks/pages/offline-demo.client-b0af77c9a59f71e5.js",
      "generatedIndex": 4092,
      "generatedMatch": "Yjs",
      "generatedLine": 1,
      "generatedColumn": 4092,
      "source": "webpack:///pages/offline-demo.client.tsx",
      "sourceLine": 124,
      "sourceColumn": 14,
      "sourceName": null,
      "snippet": "text-Aware AI Assistant\"}),(0,l.jsx)(\"li\",{children:\"✅ Real-time Collaboration (Yjs + WebSocket)\"}),(0,l.jsx)(\"li\",{children:\"✅ Offline Persistence (IndexedDB)\"}),(0,l.jsx)(\"li\",{children:\"✅ Cross-Pla",
      "strong": false
    }
  ],
  "uniqueKeysCount": 6,
  "yjsRuntimeCandidates": [],
  "allowlist": [
    "monaco-editor",
    "@monaco-editor/react",
    "jose",
    "lib0",
    "vendors-yjs-",
    "static/chunks/vendors-yjs-",
    "middleware-build-manifest",
    "middleware-react-loadable-manifest",
    "_buildManifest.js",
    "webpack/runtime/get%20javascript%20chunk%20filename",
    "webpack://udp/web/pages",
    "webpack://_N_E/pages",
    "webpack://udp/src/shared/lib",
    "webpack://_N_E/src/shared/lib",
    "polyfills-"
  ],
  "strict": false,
  "flaggedFiles": 6,
  "severity": "error"
}
